{
  "paperId": "business-0450-2021-unit2-march-qp",
  "pairedMarkSchemeId": "business-0450-2021-unit2-march-ms",
  "subjectId": "business_igcse",
  "code": "0450/22",
  "session": "February/March 2021",
  "title": "Paper 2 - Question Paper",
  "documentType": "QP",
  "totalMarks": 2,
  "timeMinutes": 90,
  "questions": [
    {
      "id": "q1",
      "number": 1,
      "type": "structured",
      "totalMarks": 1,
      "marks": 1,
      "question": "Question 1",
      "text": "Question 1",
      "parts": [
        {
          "id": "1b",
          "text": "Part 1b",
          "marks": 1,
          "type": "structured",
          "answer": "• On the gross and profit margins then Option B is better than Option A. Both margins are higher for Option B and therefore this has the higher profitability. This Option also has a higher number of orders over the year as each order is 1000 products and was ordered 10 times last year and so this Option is the better one to choose. Question Answer Marks One mark for each way (maximum of 2). Award a maximum of 3 additional marks for each explanation of how added value can be increased – one of which must be applied to this context. Relevant answers might include: Increase price (1) – explanation of why/how prices can be increased (1) such as: • improve quality of the T-shirts • improve reputation for high quality logos on the products • establish brand image • improve product features such as excellent customer service/USP Reduce input/raw material costs (1) explanation of how these can be reduced (1) such as: • buy cheaper raw materials/find cheaper suppliers of T-shirts • lower the quality of inputs such as cheaper fabric • reduce the amount of inputs needed, for example redesign the T-shirts so they do not use as much fabric For example: Reduce raw material costs (1) such as buy cheaper fabric/material (app). ST could change to a cheaper supplier of raw materials (1). This will increase the gap between price and input costs and therefore increase added value (1). Application could include: t-shirts; customers’ own designs; no other company offers guarantee of 100% satisfaction; high priced products aimed at niche markets; digital sewing machines; logo name or picture provided by customer. Note: The two ways can both come from either increased price or reduce input costs or one from each. March 2021 Question Answer Marks change from niche marketing to mass marketing. Consider the advantages of both methods. Which method should ST use? Justify your answer. Level Description Marks Sound application of knowledge and understanding of relevant business concepts using ap",
          "image": "/papers/business-0450-2021/q1-1b.png"
        }
      ],
      "image": "/papers/business-0450-2021/q1.png"
    },
    {
      "id": "q3",
      "number": 3,
      "type": "structured",
      "totalMarks": 1,
      "marks": 1,
      "question": "Question 3",
      "text": "Question 3",
      "parts": [
        {
          "id": "3b",
          "text": "Part 3b",
          "marks": 1,
          "type": "structured",
          "answer": "Sai • He has a wide range of experience as he has worked for three different clothing businesses – suggests he is a talented employee • He is able to repair digital sewing machines – so can save ST the cost of repair – but he should be focusing on managing the Operations department and not repairing machinery • Does not have a degree so may lack knowledge of how to run a department • Lacks experience of management of a department as he has only been a Supervisor and an Assistant Manager Recommendation • Vivaan should be chosen as he has the most experience and this may help to increase output and improve efficiency for ST. Aarav lacks experience even though he is well qualified in management and Sai has not been an Operations Manager only an Assistant so also lacks the relevant experience when compared to Vivaan. • Aarav should be chosen as he is well qualified and should be able to communicate well with employees which is required due to the previous Operations Manager not motivating employees. Motivation and productivity need to be increased and Aarav seems to be more of a people person, whereas the other two applicants are skilled in using and repairing machines which is not required for the Operations Manager who should be focusing on running the factory. • Sai should be chosen as he is very experienced having worked in 3 different clothing factories and should be able to easily cope with gaining promotion to the Operations Manager having been an Assistant Manager for 2 years. This is better experience than the other two applicants as Aarav only has one years’ experience and not as an Operations Manager only an Assistant and Vivaan has only worked for one business so may lack new ideas from other businesses. March 2021 Question Answer Marks Award one mark for reason (maximum of 4). Award a maximum of 1 additional mark for each explanation in the context of ST of the reason of why quality is important. Relevant answers might include: • Establishes a brand image –",
          "image": "/papers/business-0450-2021/q3-3b.png"
        }
      ],
      "image": "/papers/business-0450-2021/q3.png"
    }
  ],
  "_meta": {
    "parser": "structured",
    "partCount": 2,
    "questionCount": 2
  },
  "assets": {
    "basePath": "/papers/business-0450-2021",
    "qpPdf": "/pdf-pastpaer-q&a/O-Level/BusinessStudies-0450/BusinessStudies-0450-2021-unit2-2021-03-qp.pdf"
  },
  "unit": "Unit 2"
}