{
  "paperId": "mathematics-0580-2024-unit4-november-qp",
  "pairedMarkSchemeId": "mathematics-0580-2024-unit4-november-ms",
  "subjectId": "mathematics_igcse",
  "code": "0580/41",
  "session": "October/November 2024",
  "title": "Paper 4 - Question Paper",
  "documentType": "QP",
  "totalMarks": 4,
  "timeMinutes": 90,
  "questions": [
    {
      "id": "q1",
      "number": 1,
      "type": "structured",
      "totalMarks": 1,
      "marks": 1,
      "question": "Question 1",
      "text": "Question 1",
      "parts": [
        {
          "id": "1c",
          "text": "Part 1c",
          "marks": 1,
          "type": "structured",
          "answer": "5.5 or or 5ВЅ M1 for 2x = 15 вЂ“ 4 oe or x+= oe M1 dep for reaching ax = b FT their first step M1 for 7 + ( 8)в€’ oe пЃ›пЃќ ()Pdп‚±в€’ oe final answer B1 for P вЂ“ d = m oe M1 for cube both sides M1 for square root leading to final answer in y = 1 wrong position 90 clockwise oe [centre] (2, 4) oe 3 B1 for each M1 for 5, 15, 30, 45, 65 soi M1 for fxпЃ“ M1 dep for their fxпЃ“ Г· 120 dep on 2 nd M1 October/November 2024 Question Answer Marks Partial Marks B3 for [height = ] 1.75 OR M2 for [90 вЂ“ ](10 Г— 1.3 + 20 Г— 1.5 + 30 Г— 0.4) oe or M1 for 10 Г— 1.3 or 20 Г— 1.5 or 30 Г— 0.4 M1dep for their frequency Г· 20 dep on at least M1 After 0 scored SC1 for bar of correct width and height between 1.7 and 1.8 M1 for пЃ›пЃќ 11.25 11.25 18.75 20 п‚ґ ++ oe or 0.556 or 0.5555 to 0.5556 M2 for 20 25 15[ 60] п‚ґ п‚ґ oe or M1 for 20 Г— 25 or for their distance Г· (15 [Г— 60]) oe October/November 2024 Question Answer Marks Partial Marks B3 for [h]oe or 160 [mins] or 9600[s] Or M3 for 5000 Г· (18.75 Г— 25 Г— 4)[h] oe or 5000 Г· (18.75 Г— 25 Г· 15)[mins] oe or 5000 Г· ((18.75 Г— 25 Г— 4) Г· (60 Г— 60))[secs] oe Or M2 for (18.75 Г— 25 Г— 4)[m/h] oe or (18.75 Г— 25 Г· 15)[m/min] oe or (18.75 Г— 25 Г— 4) Г· (60 Г— 60))[m/sec] oe Or B1 for 200 or 1 km =1000m soi After 0 scored SC1 for time Figs 267 or figs 2666 to 2667 or figs 16 or figs 96 Approach 2 B3 for 160 [mins] Or M3 for 15 Г— 5000 Г· (18.75 Г— 25) [mins] oe Or M2 for 5000 Г· (18.75 Г— 25) oe Or B1 for 200 or 1 km =1000m soi After 0 scored SC1 for time figs 16 M2 for 20 Г— 100 5 в€’ пѓ¦пѓ¶ пѓ§пѓ· пѓЁпѓё oe or M1 for 20 Г— 100 5 k в€’ пѓ¦пѓ¶ пѓ§пѓ· пѓЁпѓё where k is 2, or or for 20 Г— 100 5 в€’ пѓ¦пѓ¶ пѓ§пѓ· пѓЁпѓё oe seen and spoiled M2 for 425 to 450 10 0.5+ or 450 12.5 10 to 11 в€’ or 425 to 450 or 450 12.5 600 660to в€’ or M1 for 10.5 or 9.5 or 437.5 or 462.5 or 630[s] or 570[s] October/November 2024 Question Answer Marks Partial Marks",
          "image": "/papers/mathematics-0580-2024/q1-1c.png"
        }
      ],
      "image": "/papers/mathematics-0580-2024/q1.png"
    },
    {
      "id": "q5",
      "number": 5,
      "type": "structured",
      "totalMarks": 2,
      "marks": 2,
      "question": "Question 5",
      "text": "Question 5",
      "parts": [
        {
          "id": "5a",
          "text": "Part 5a",
          "marks": 1,
          "type": "structured",
          "answer": "5 oe of branches 2 B1FT for one pair of branches of first stage or second stage correct oe M2FT for their 3 35 5 8 88 8 пѓ¦пѓ¶ пѓ¦пѓ¶ п‚ґ + п‚ґ пѓ§пѓ· пѓ§пѓ· пѓЁпѓё пѓЁпѓё oe or M1FT for one correct product seen",
          "image": "/papers/mathematics-0580-2024/q5-5a.png"
        },
        {
          "id": "5c",
          "text": "Part 5c",
          "marks": 1,
          "type": "structured",
          "answer": "15 oe M2 FT for 3 2 5 8 7 6 kп‚ґ п‚ґ п‚ґ where k is 1, 2 or or M1FT for andand seen oe or for showing the 3 possible combinations If 0 scored, SC1 for answer oe",
          "image": "/papers/mathematics-0580-2024/q5-5c.png"
        }
      ],
      "image": "/papers/mathematics-0580-2024/q5.png"
    },
    {
      "id": "q6",
      "number": 6,
      "type": "structured",
      "totalMarks": 1,
      "marks": 1,
      "question": "Question 6",
      "text": "Question 6",
      "parts": [
        {
          "id": "6a",
          "text": "Part 6a",
          "marks": 1,
          "type": "structured",
          "answer": "22 4208302 420 830 cos106+ в€’ п‚ґ п‚ґ п‚ґ oe M2 or M1 for 4208302 420 830 cos106+в€’ п‚ґ п‚ґ п‚ґ oe A1 for 1 057 474 .... 1028.3... A1 or M2 for 1150sin 62 sin[] ACB= oe or M1 for sin 62sinACB = oe October/November 2024 Question Answer Marks Partial Marks B3 for answer 2476.9... or M2 for 420 830 sin10641 500 210 000 P п‚ґ п‚ґ п‚ґп‚ґ= oe or M1 for 420 830 sin106 п‚ґ п‚ґ п‚ґ oe and completion to 2x + 3y в‰Ґ 450 with no errors seen and y = 90 solid ruled line and x + y = 240 solid ruled line and 2x + 3y = 450 solid ruled line B5 B1 for x = 180 broken straight line B1 for y = 90 solid ruled line B1 for x + y = 240 solid ruled line B2 for 2x + 3y = 450 solid ruled line or B1 for line with a negative gradient passing through (0, 150) or (225, 0) Correct region indicated B2 B1 for region satisfying 3 of the inequalities or M1 for their 150 Г— 10 + their 90 Г— 30 = 20 + 16 or better Or B1 for 6 or -6 October/November 2024 Question Answer Marks Partial Marks xв€’ oe final answer M1 for x = 7 вЂ“ 3y or y x=в€’ or y вЂ“ 7 = вЂ“ 3x oe or better вЂ“ 42x + 34 final answer 3 M1 for (7 вЂ“ 3x) вЂ“ 16 [+ 1] oe B1 for 49 вЂ“ 21x вЂ“ 21x + 9x +k and y вЂ“ intercept and turning point at y = вЂ“ B1 for correct parabola shape B2 for roots at вЂ“4 and 4 on graph and no extras or B1 for (x вЂ“ 4) (x + 4) [= 0] or for one correct root on graph or for -4 and 4 seen B1 for turning point at (0, вЂ“16) M1 for x = -3 substituted into their derivative B1 for (вЂ“ 3, вЂ“7) soi M1 substitution of (вЂ“ 3, their вЂ“7) into y = their вЂ“6x + c oe dep on 2 nd M1 axis B1 for correct shape October/November 2024 Question Answer Marks Partial Marks oe or M1 for 10 Г— 8 oe or 10 Г— 17 oe or 8 Г— 17 oe M3 for tan [GAC] = 108+ oe or M2 for 10 + 8 oe or for 10 + 8 + 17 oe or M1 for recognising angle GAC is required + 8 + 17 oe OR B1 for QG = 2 soi or HQ = 8 M1 for (5 вЂ“ 2) + 8 or (5 вЂ“ 2) + 17 + 5x вЂ“187 [= 0] M2 M1 for (2x + 3)(x + 1) = 190 (2x вЂ“17)(x + 11) [= 0] oe M1 Leading to x = 8.5 with no errors A1 or B1 for 9.5 and 20 ПЂ п‚ґ r вЂ“ r п‚ґ sin50 = 30 oe M3 M1 for ПЂ п‚ґ r M1 for r п‚ґ sin50 o",
          "image": "/papers/mathematics-0580-2024/q6-6a.png"
        }
      ],
      "image": "/papers/mathematics-0580-2024/q6.png"
    }
  ],
  "_meta": {
    "parser": "structured",
    "partCount": 4,
    "questionCount": 3
  },
  "assets": {
    "basePath": "/papers/mathematics-0580-2024",
    "qpPdf": "/pdf-pastpaer-q&a/O-Level/Mathematics-0580/Mathematics-0580-2024-unit4-2024-11-qp.pdf"
  },
  "unit": "Unit 4"
}