{
  "paperId": "mathematics-0580-2017-unit2-june-p23-qp",
  "pairedMarkSchemeId": "mathematics-0580-2017-unit2-june-p23-ms",
  "subjectId": "mathematics_igcse",
  "code": "0580/23",
  "session": "May/June 2017",
  "title": "Paper 2 - Question Paper",
  "documentType": "QP",
  "totalMarks": 8,
  "timeMinutes": 90,
  "questions": [
    {
      "id": "q9",
      "number": 9,
      "type": "structured",
      "totalMarks": 1,
      "marks": 1,
      "question": "9 (a) GH 6 4 = - cm Find (i) GH5 , fp [1] (ii) HG .",
      "text": "9 (a) GH 6 4 = - cm Find (i) GH5 , fp [1] (ii) HG .",
      "parts": [
        {
          "id": "9b",
          "text": "Part 9b",
          "marks": 1,
          "type": "structured",
          "answer": "−4 0580/23 May/June 2017 Question Answer Marks Part Marks M1 for 567180xxx++=oe or 567++ or B1 for angles 50, 60 and 70 1FT FT 7 × their (a) provided 0 < their answer < 180 11 Correct region SC1 for R not marked and reverse shading",
          "image": "/papers/mathematics-0580-2017/q9-9b.png"
        }
      ],
      "image": "/papers/mathematics-0580-2017/q9.png"
    },
    {
      "id": "q12",
      "number": 12,
      "type": "structured",
      "totalMarks": 2,
      "marks": 2,
      "question": "Question 12",
      "text": "Question 12",
      "parts": [
        {
          "id": "12a",
          "text": "Part 12a",
          "marks": 1,
          "type": "structured",
          "answer": "312x+ final answer",
          "image": "/papers/mathematics-0580-2017/q12-12a.png"
        },
        {
          "id": "12b",
          "text": "Part 12b",
          "marks": 1,
          "type": "structured",
          "answer": "2431x+ final answer M1 for 34(6 7)x++ 13 150 M2 for 0.512    oe or 0.512    oe or M1 for scale factor 0.512    oe or 0.512 [1]    oe k+2 × [0].63 && − 10 k × [0].63 && oe where k > 1 M1 or equivalent fraction A1 e.g. but not B1 15 35.8 or 35.77.... M2 for [sin =] 24 sin 71.8 × or M1 for sin 71.8sin x = oe",
          "image": "/papers/mathematics-0580-2017/q12-12b.png"
        }
      ],
      "image": "/papers/mathematics-0580-2017/q12.png"
    },
    {
      "id": "q16",
      "number": 16,
      "type": "structured",
      "totalMarks": 1,
      "marks": 1,
      "question": "16 (a) Solve the inequality. xx1337H++ ...................................................[2] (b) List the positive integers that satisfy",
      "text": "16 (a) Solve the inequality. xx1337H++ ...................................................[2] (b) List the positive integers that satisfy",
      "parts": [
        {
          "id": "16a",
          "text": "16 (a) Solve the inequality. xx1337H++ ...................................................[2] (b) List the positive integers that satisfy",
          "marks": 1,
          "type": "structured",
          "answer": "x ⩽ 3 final answer M1 for 13 − 7 ⩾ 3x − x oe 1FT correct answer or FT their answer to (a) 0580/23 May/June 2017 Question Answer Marks Part Marks p + q M1 for PZ = (q − p) oe or QZ = (p − q) oe M1 for correct route from O to Z or identifying OZ 18 3000 M2 for 12.5 () 200 280 ×+ oe or M1 for part area 19 common denominator 12 B1 accept k × 12 throughout one correct from or oe M1 accept k k or k k cao A2 A1 for or k k",
          "image": "/papers/mathematics-0580-2017/q16-16a.png"
        }
      ],
      "image": "/papers/mathematics-0580-2017/q16.png"
    },
    {
      "id": "q20",
      "number": 20,
      "type": "structured",
      "totalMarks": 2,
      "marks": 2,
      "question": "Question 20",
      "text": "Question 20",
      "parts": [
        {
          "id": "20b",
          "text": "Part 20b",
          "marks": 1,
          "type": "structured",
          "answer": "3 2x final answer",
          "image": "/papers/mathematics-0580-2017/q20-20b.png"
        },
        {
          "id": "20c",
          "text": "Part 20c",
          "marks": 1,
          "type": "structured",
          "answer": "4 15y final answer B1 for 15 k y or kyas final answer (k ≠ 0) 104 5 2−×× oe or better B1 If completing the square: B1 for () 1x+ oe B1 for −+− or −− − oe 2(5) q−+ or 2(5) q−− oe B1 − 0.23, −1.77 final ans cao B1B1 SC1 for − 0.2 or − 0.225... and −1.8 or −1.774... or −1.775 or 0.23 and 1.77 as answer or − 0.23 and −1.77 seen in working Maximum score without working is 2 22 35.3 or 35.26... M3 for [tan =] + oe or M1 for [] 2626AC=+oe and M1 for [tan =] 26 ÷ their AC oe or for angle CAG indicated 0580/23 May/June 2017 Question Answer Marks Part Marks",
          "image": "/papers/mathematics-0580-2017/q20-20c.png"
        }
      ],
      "image": "/papers/mathematics-0580-2017/q20.png"
    },
    {
      "id": "q23",
      "number": 23,
      "type": "structured",
      "totalMarks": 2,
      "marks": 2,
      "question": "23 (a) Simplify. () () x x 6 46 2 - - ...................................................[1] (b) Expand the brackets and simpl",
      "text": "23 (a) Simplify. () () x x 6 46 2 - - ...................................................[1] (b) Expand the brackets and simpl",
      "parts": [
        {
          "id": "23a",
          "text": "23 (a) Simplify. () () x x 6 46 2 - - ...................................................[1] (b) Expand the brackets and simpl",
          "marks": 1,
          "type": "structured",
          "answer": "() 46x− or 4x − 24 as final answer",
          "image": "/papers/mathematics-0580-2017/q23-23a.png"
        },
        {
          "id": "23b",
          "text": "Part 23b",
          "marks": 1,
          "type": "structured",
          "answer": "2 2326xx++ final answer B2 for 4416xxx+++or better or B1 for 1510x+ 24 1.96 cao M4 for ( ( 2500 1.6 3   ×× +     −       ) − 1) [× 100] oe or 1.96...or [0].0196... or 101.96... or 1.0196... or M3 for 2500 1.6 3 ×× + or B2 for [SI =] 120 or [CI total=] 2120 or M1 for 2500 3 1.6 ×× and M1 for 2000 () k×",
          "image": "/papers/mathematics-0580-2017/q23-23b.png"
        }
      ],
      "image": "/papers/mathematics-0580-2017/q23.png"
    }
  ],
  "_meta": {
    "parser": "structured",
    "partCount": 8,
    "questionCount": 5
  },
  "assets": {
    "basePath": "/papers/mathematics-0580-2017",
    "qpPdf": "/pdf-pastpaer-q&a/O-Level/Mathematics-0580/Mathematics-0580-2017-unit2-2017-06-22-qp.pdf"
  },
  "unit": "Unit 2"
}