{
  "paperId": "physics-0625-2017-unit5-march-qp",
  "pairedMarkSchemeId": "physics-0625-2017-unit5-march-ms",
  "subjectId": "physics_igcse",
  "code": "0625/52",
  "session": "February/March 2017",
  "title": "Paper 5 - Question Paper",
  "documentType": "QP",
  "totalMarks": 9,
  "timeMinutes": 90,
  "questions": [
    {
      "id": "q1",
      "number": 1,
      "type": "structured",
      "totalMarks": 2,
      "marks": 2,
      "question": "1 (a) Measure the height h o of the illuminated triangle, as indicated in Fig. 3.1. h o = ...........................................................[1] (b) Arrange the apparatus as shown in Fig. 3.1. • Set the distance u between the illuminated triangle and the lens to 20.0 cm. • Place the screen near the lens. Move the screen",
      "text": "1 (a) Measure the height h o of the illuminated triangle, as indicated in Fig. 3.1. h o = ...........................................................[1] (b) Arrange the apparatus as shown in Fig. 3.1. • Set the distance u between the illuminated triangle and the lens to 20.0 cm. • Place the screen near the lens. Move the screen",
      "parts": [
        {
          "id": "1c",
          "text": "Part 1c",
          "marks": 1,
          "type": "structured",
          "answer": "any 2 appropriate precautions: stir before reading, keep thermometer at same level, set eye to same level as / perpendicular / right angles to scale, wait until reading stops rising (at start ), position clock so that thermometer and clock can be easily seen correct mention of comparative temperature change over 180 s",
          "image": "/papers/physics-0625-2017/q1-1c.png"
        },
        {
          "id": "1e",
          "text": "Part 1e",
          "marks": 1,
          "type": "structured",
          "answer": "any suitable improvement to apparatus or procedure relating to comparison, e.g.: • measure water into test-tube / beaker, • use same volume of water in test-tube / beaker, • use same starting temperatures in tubes, • ensure all water in tube below level of water in beaker, • use insulation / lid on beaker matching explanation, e.g.: • ensure same amount of water being used each time, • cooling rates different / owtte at different volumes / temps, • all water in tube has same surrounding temperature, • keeps water in beaker at (more) constant temperature Total: / March 2017 l values in order V all < 4.00 V and to 1dp at least I all < 1.00 A and to 2dp at least arrow on wire between the inside edge of each crocodile clip",
          "image": "/papers/physics-0625-2017/q1-1e.png"
        }
      ],
      "image": "/papers/physics-0625-2017/q1.png"
    },
    {
      "id": "q2",
      "number": 2,
      "type": "structured",
      "totalMarks": 2,
      "marks": 2,
      "question": "Question 2",
      "text": "Question 2",
      "parts": [
        {
          "id": "2b",
          "text": "Part 2b",
          "marks": 1,
          "type": "structured",
          "answer": "correct calculations of R consistent 2 or consistent 3 sig. figs. correct calculations of r all within 10% justification matching statement and results (‘within limits of experimental accuracy’ / owtte)",
          "image": "/papers/physics-0625-2017/q2-2b.png"
        },
        {
          "id": "2d",
          "text": "Part 2d",
          "marks": 1,
          "type": "structured",
          "answer": "any suitable precaution: reduce current / voltage, use longer / thinner resistance wires, Total: / March 2017",
          "image": "/papers/physics-0625-2017/q2-2d.png"
        }
      ],
      "image": "/papers/physics-0625-2017/q2.png"
    },
    {
      "id": "q3",
      "number": 3,
      "type": "structured",
      "totalMarks": 5,
      "marks": 5,
      "question": "Question 3",
      "text": "Question 3",
      "parts": [
        {
          "id": "3a",
          "text": "Part 3a",
          "marks": 1,
          "type": "structured",
          "answer": "sensible value for h O (1.0 to 2.5 cm)",
          "image": "/papers/physics-0625-2017/q3-3a.png"
        },
        {
          "id": "3b",
          "text": "Part 3b",
          "marks": 1,
          "type": "structured",
          "answer": "h I values all decreasing",
          "image": "/papers/physics-0625-2017/q3-3b.png"
        },
        {
          "id": "3c",
          "text": "Part 3c",
          "marks": 1,
          "type": "structured",
          "answer": "M calculations correct axes labelled with quantity and unit appropriate scales (plots occupying at least ½ grid) plots all correct to within ½ small square well judged line and single, continuous thin line",
          "image": "/papers/physics-0625-2017/q3-3c.png"
        },
        {
          "id": "3e",
          "text": "Part 3e",
          "marks": 1,
          "type": "structured",
          "answer": "construction line(s) clearly seen on graph u in range 25.0 to 35.0 (cm)",
          "image": "/papers/physics-0625-2017/q3-3e.png"
        },
        {
          "id": "3f",
          "text": "Part 3f",
          "marks": 1,
          "type": "structured",
          "answer": "any appropriate difficulty: e.g. hand / ruler in way of image matching improvement: e.g. use translucent screen and view from behind, fix ruler / grid to screen Total: / March 2017 apparatus: MP1 springs made by winding wire around rod (or similar) method: MP2 apply load, measure length / extension of spring MP3 repeat for spring(s) of different material MP4 record results in suitable annotated table / bar chart / graph control variables: MP5 mark gained for any two of: unstretched length of spring, diameter of wire, coil spacing, load / range of loads used diameter of spring MP6 precautions / difficulties / additional points: MP7 any two from: clamp retort stand / might topple, use small loads / spring might overstretch / spring too weak / use loads which don’t overstretch spring to support loads need to apply force smoothly / slowly, suggested range of loads, workable arrangement for applying load to spring (e.g. small loop at end of spring) trial experiment to find (range of) loads to use how to determine extension of spring, repeat each reading and take average, at least 5 loads for each sample if producing graph Total:",
          "image": "/papers/physics-0625-2017/q3-3f.png"
        }
      ],
      "image": "/papers/physics-0625-2017/q3.png"
    }
  ],
  "_meta": {
    "parser": "structured",
    "partCount": 9,
    "questionCount": 3
  },
  "assets": {
    "basePath": "/papers/physics-0625-2017",
    "qpPdf": "/pdf-pastpaer-q&a/O-Level/Physics-0625/Physics-0625-2017-unit5-2017-03-qp.pdf"
  },
  "unit": "Unit 5"
}