{
  "paperId": "physics-0625-2019-unit4-june-qp",
  "pairedMarkSchemeId": "physics-0625-2019-unit4-june-ms",
  "subjectId": "physics_igcse",
  "code": "0625/41",
  "session": "May/June 2019",
  "title": "Paper 4 - Question Paper",
  "documentType": "QP",
  "totalMarks": 9,
  "timeMinutes": 90,
  "questions": [
    {
      "id": "q1",
      "number": 1,
      "type": "structured",
      "totalMarks": 2,
      "marks": 2,
      "question": "1 (a) Define acceleration. ................................................................................................................................................... ............................................................................................................................................. [1] (b) On Fig. 1.2, sketch a graph to show how the sp",
      "text": "1 (a) Define acceleration. ................................................................................................................................................... ............................................................................................................................................. [1] (b) On Fig. 1.2, sketch a graph to show how the sp",
      "parts": [
        {
          "id": "1a",
          "text": "1 (a) Define acceleration. ................................................................................................................................................... ............................................................................................................................................. [1] (b) On Fig. 1.2, sketch a graph to show how the sp",
          "marks": 1,
          "type": "structured",
          "answer": "change of velocity per unit time OR vu t − B1",
          "image": "/papers/physics-0625-2019/q1-1a.png"
        },
        {
          "id": "1b",
          "text": "Part 1b",
          "marks": 1,
          "type": "structured",
          "answer": "line starts at origin and is asymptotic to x -axis B1 increasing gradient initially and no decrease B1 constant and clearly positive gradient finally B1 no external forces OR isolated system B1 sum of momenta / (total) momentum remains constant B1 rocket gains (upward) momentum B1 (ejected) gas gains equal (quantity of) momentum in opposite direction OR momentum of gas decreases by equal amount B1 0625/41 May/June 2019",
          "image": "/papers/physics-0625-2019/q1-1b.png"
        }
      ],
      "image": "/papers/physics-0625-2019/q1.png"
    },
    {
      "id": "q2",
      "number": 2,
      "type": "structured",
      "totalMarks": 2,
      "marks": 2,
      "question": "Question 2",
      "text": "Question 2",
      "parts": [
        {
          "id": "2a",
          "text": "Part 2a",
          "marks": 1,
          "type": "structured",
          "answer": "( W =) mg OR 3.4 × × C1 3.4 × N A1 Fx in any form OR (moment) = Fx OR 0.50 (seen) C1 3.4 × × (1.8 – 1.3) OR 3.4 × × 0.50 C1 1.7 × N m A1 1. (the point) where (all) the mass can be considered to be concentrated B1 2. 1.7 × / (1.3 + 0.70) OR 1.7 × / (2.0) C1 8.5 × N A1",
          "image": "/papers/physics-0625-2019/q2-2a.png"
        },
        {
          "id": "2c",
          "text": "Part 2c",
          "marks": 1,
          "type": "structured",
          "answer": "(moment / it) increases B1 perpendicular distance (between P and line of action of) W increases B1 0625/41 May/June 2019",
          "image": "/papers/physics-0625-2019/q2-2c.png"
        }
      ],
      "image": "/papers/physics-0625-2019/q2.png"
    },
    {
      "id": "q3",
      "number": 3,
      "type": "structured",
      "totalMarks": 1,
      "marks": 1,
      "question": "Question 3",
      "text": "Question 3",
      "parts": [
        {
          "id": "3a",
          "text": "Part 3a",
          "marks": 1,
          "type": "structured",
          "answer": "(air) molecules / they move / collide B1 (air) molecules / they collide with cube / (upper) surface (of cube) / wall B1 impulse exerted (on surface) OR momentum change (of molecules) B1 p = h ρ g in any form OR ( p =) h ρ g OR 0.028 × × C1 Pa A1 F = pA in any form words, symbols or numbers OR ( F =) pA OR × 4.0 OR × 0.040 OR × OR × 1.6 × –3 C1 0.67 N A1 W = Fd in any form words, symbols or numbers OR (W =) Fd OR 0.67 × 0.034 C1 0.023 A1 lifting liquid as well OR friction between liquid and container / pipe B1 0625/41 May/June 2019 E = mc ( ∆ ) T in any form words, symbols or numbers OR ( E =) mc ( ∆ ) T OR 0.23 × 0.72 × C1 J A1 t = E / P in any form words, symbols or numbers OR ( t =) E / P or 91 / 2.4 C1 s A1 2. (thermal) energy is used to increase the temperatur e of / lost to cylinder / piston / heater / surroundings B1 it / piston moves to the right / away from heater OR accelerates (to right) M1 pressure (of gas) greater / pressure greater (on left) / resultant force to right A1 V = p V / p in any form OR ( V =) p V / p OR 2.9 × × 1.9 × –4 / 1.0 × C1 5.5 × –4 m A1 0625/41 May/June 2019 two from: occurs throughout the liquid OR bubbles formed occurs at one temperature / boiling point does not produce cooling OR unaffected by draught / surface area / humidity B2 (more) energetic molecules escape (from the liquid) OR molecules gain energy and escape OR molecules overcome intermolecular forces / break bonds B1 average speed decreases OR molecules with less (kinetic) energy left behind B1 temperature of liquid decreases B1 (thermal) energy conducted / gained from skin / body OR (thermal) energy lost by skin / body B1",
          "image": "/papers/physics-0625-2019/q3-3a.png"
        }
      ],
      "image": "/papers/physics-0625-2019/q3.png"
    },
    {
      "id": "q5",
      "number": 5,
      "type": "structured",
      "totalMarks": 1,
      "marks": 1,
      "question": "Question 5",
      "text": "Question 5",
      "parts": [
        {
          "id": "5b",
          "text": "Part 5b",
          "marks": 1,
          "type": "structured",
          "answer": "molecules touching OR no space between molecules B1 large (repulsive / intermolecular) forces (when moved closer) B1 0625/41 May/June 2019",
          "image": "/papers/physics-0625-2019/q5-5b.png"
        }
      ],
      "image": "/papers/physics-0625-2019/q5.png"
    },
    {
      "id": "q6",
      "number": 6,
      "type": "structured",
      "totalMarks": 1,
      "marks": 1,
      "question": "Question 6",
      "text": "Question 6",
      "parts": [
        {
          "id": "6a",
          "text": "Part 6a",
          "marks": 1,
          "type": "structured",
          "answer": "idea of one side of wavefront enters / hits solid first OR wavefront does not all hit the solid all at once; B1 idea of this side slowed down first OR this side delayed relative to other side B1 angle of wave(front) changes OR different parts of wavefront delayed by different amounts B1 n = sini sinr in any form OR n sin θ = n sin θ OR 1.3 = sin67° sinr OR ( r = )sin –1 (sin67° / 1.3) OR sin –1 (0.71) C1 45° A1 v ts = c / n in any form OR ( v ts =) c / n OR 3.0 × / 1.3 C1 2.3 × OR 3.0 × / 1.3 C1 λ = v / f in any form OR ( λ =) v / f OR 2.3 × / 5.7 × OR 3.0 × / (1.3 × 5.7 × ) C1 4.0 × –7 m A1 OR (alternative approach) λ = v / f in any form OR ( λ =) v / f OR 3.0 × / 5.7 × C1 5.3 × –7 OR 3.0 × / 5.7 × C1 λ g = λ a / n in any form OR ( λ g =) λ a / n OR 5.3 × –7 / 1.3 OR 3.0 × / (1.3 × 5.7 × ) C1 4.0 × –7 m A1 0625/41 May/June 2019 c.a.o. B1 V X = V B1 V X = E – V in any form B1 R + 1/ R = 1/ R tot OR ( R tot =) R R / ( R + R ) OR 1/15 + 1/30 = 1/ R tot OR (15 × 30) / (15 + 30) C1 ( Ω ) OR 10 + 20 C1 Ω A1 I = V / R in any form OR ( I =) V / R OR 6.0 / 30 C1 0.20 A A1",
          "image": "/papers/physics-0625-2019/q6-6a.png"
        }
      ],
      "image": "/papers/physics-0625-2019/q6.png"
    },
    {
      "id": "q7",
      "number": 7,
      "type": "structured",
      "totalMarks": 1,
      "marks": 1,
      "question": "Question 7",
      "text": "Question 7",
      "parts": [
        {
          "id": "7d",
          "text": "Part 7d",
          "marks": 1,
          "type": "structured",
          "answer": "resistance of X decreases B1 ammeter reading / it increases and (total) resistance (of circuit) decreases / more voltage across 20 Ω resistor B1 0625/41 May/June 2019 B1 coil / wire cuts (magnetic) field OR changing (magnetic) field (through coil) B1 e.m.f. / voltage induced OR produced by electromagnetic induction B1 (plane of coil) horizontal OR in position shown in diagram coil cutting magnetic field the fastest B1 B1",
          "image": "/papers/physics-0625-2019/q7-7d.png"
        }
      ],
      "image": "/papers/physics-0625-2019/q7.png"
    },
    {
      "id": "q8",
      "number": 8,
      "type": "structured",
      "totalMarks": 1,
      "marks": 1,
      "question": "Question 8",
      "text": "Question 8",
      "parts": [
        {
          "id": "8b",
          "text": "Part 8b",
          "marks": 1,
          "type": "structured",
          "answer": "current in coil OR energy supplied to / lost from lamp B1 current in (magnetic) field experiences a force student must do more work / supply more energy / more energy needed B1 opposes the change causing it greater force to do more work B1 0625/41 May/June 2019 mark both explanation and deduction together nucleus is very small B1 very few α -particles hit or pass near to a nucleus B1 mark both explanation and deduction together nucleus is charged B1 (charged) α -particles experience a force B1 mark both explanation and deduction together centre / (small) part of atom OR nucleus includes most of the mass of the atom / is (very) dense B1 ( α -particles move and) nucleus stays still B1 two from: opposite direction (much) smaller deflection undergo deflections of similar magnitude B2",
          "image": "/papers/physics-0625-2019/q8-8b.png"
        }
      ],
      "image": "/papers/physics-0625-2019/q8.png"
    }
  ],
  "_meta": {
    "parser": "structured",
    "partCount": 9,
    "questionCount": 7
  },
  "assets": {
    "basePath": "/papers/physics-0625-2019",
    "qpPdf": "/pdf-pastpaer-q&a/O-Level/Physics-0625/Physics-0625-2019-unit4-2019-06-qp.pdf"
  },
  "unit": "Unit 4"
}