{
  "paperId": "wac11-jan-2020-unit1-qp",
  "pairedMarkSchemeId": "wac11-jan-2020-unit1-ms",
  "subjectId": "accounting_ial_pearson",
  "code": "WAC11/01",
  "session": "January 2020",
  "title": "Unit 1 - Question Paper",
  "documentType": "QP",
  "totalMarks": 4,
  "timeMinutes": 90,
  "questions": [
    {
      "id": "q1",
      "number": 1,
      "type": "structured",
      "totalMarks": 1,
      "marks": 1,
      "question": "1 (a) Prepare the journal entries to correct the errors found on 31 December 2019. Narratives are not required. (6) .................................................................................................................................................................................................................................................................................... .....",
      "text": "1 (a) Prepare the journal entries to correct the errors found on 31 December 2019. Narratives are not required. (6) .................................................................................................................................................................................................................................................................................... .....",
      "parts": [
        {
          "id": "1a",
          "text": "1 (a) Prepare the journal entries to correct the errors found on 31 December 2019. Narratives are not required. (6) .................................................................................................................................................................................................................................................................................... .....",
          "marks": 1,
          "type": "structured",
          "answer": "AO2(6) AO2: Six marks for correct narrative and numerical adjustment General Journal Dr Cr £ £ Global ICT 1 800 (1)AO2 Purchases returns 1 800 (1)AO2 Drawings 900 (1)AO2 Wages 900 (1)AO2 Electricity and water 2 300 (1)AO2 Bank 2 300 (1)AO2 (6) (b)(i) AO1:(4) AO2(9) :AO3(2) AO1: Four marks for recording balances AO2: Nine marks for adjusting balances AO3: Two marks for calculating the cost of sales and wages Statement of Profit or Loss and Other Comprehensive Income for the year ended 31 December 2019 £ £ Revenue 309 000 (1)AO1 Opening inventory 37 600 Purchases 216 000 Purchase returns 20 300 + 1 800 (22 100) (1)AO2 231 500 Closing inventory ( 51 100) Cost of sales (180 400) (1)AO3+W Gross profit 128 600 (1 of)AO1+W Wages 40 800 - 900 + 3 700 43 600 (1)AO3 Management salaries 25 000 (1)AO1 Electricity and water 9 700 + 2 300 12 000 (1)AO2 Premises running costs 6 900 (1)AO1 Advertising expenses 17 000 – 2 400 14 600 (1)AO2 Bank loan interest 1 700 +1 300 3 000 (1)AO2 Irrecoverable debt 2 500 (1)AO2 Increase in allowance for irrecoverable debts 800 (1)AO2 Depreciation: Premises 1 600 (1)AO2 Computers and equipment 4 000 (1)AO2 Fixtures and fittings 2 400 (1)AO2 (116 400) Profit for the year 12 200 (15) (ii) AO1:(5) AO2(12) :AO3(1) AO1: Five marks for recording balances AO2: Twelve marks for calculating and recording balances AO3: One mark for calculating trade receivables less allowance Statement of Financial Position at 31 December 2019 Non-current assets Cost Accumulated Carrying depreciation value £ £ £ Premises 80 000 23 600 56 400 (1of)AO2 Computers and equipment 30 000 18 000 12 000 (1of)AO2 Fixtures and fittings 16 000 12 000 4 000 (1of)AO2 126 000 53 600 72 400 Current assets Inventory 51 100 (1)AO1 Trade receivables 37 500 – 2 500 35 000 (1)AO2 Less Allowance for ID (1 400) 33 600 (1 of)AO3 Other receivables: 2 400 (1)AO2 Bank and cash 10 350 - 2 300 8 050 (1)AO2 95 150 Total assets 167 550 Capital 80 000 (1)AO1 Current account: Balance 6 700 (1)AO1 Net prof",
          "image": "/papers/wac11-jan-2020/q1-1a.png"
        }
      ],
      "image": "/papers/wac11-jan-2020/page-02.png"
    },
    {
      "id": "q3",
      "number": 3,
      "type": "structured",
      "totalMarks": 1,
      "marks": 1,
      "question": "3 (a) State two disadvantages of not maintaining double entry books. (2) 1 ............................................................................................................................................................................................................................................................................... ..................................................",
      "text": "3 (a) State two disadvantages of not maintaining double entry books. (2) 1 ............................................................................................................................................................................................................................................................................... ..................................................",
      "parts": [
        {
          "id": "3a",
          "text": "3 (a) State two disadvantages of not maintaining double entry books. (2) 1 ............................................................................................................................................................................................................................................................................... ..................................................",
          "marks": 1,
          "type": "structured",
          "answer": "AO1:(2) AO1: Two marks for stating disadvantages of not maintaining double entry books. No information about expenditure or income Inadequate information to manage the business Individual expense totals paid not known Profit to date cannot be calculated Amount owing to trade payables/ by trade receivables cannot be verified 2 x 1 Mark NOT Discussion about errors. (2) (b) (i) AO1:(2) AO2(5) :AO3(1) AO1: Two marks for recording equipment and balancing the account AO2: Five marks for calculating and recording entries AO3: One mark for calculating the payment to the trade payables Summarized Bank Account Date Details £ Date Details £ 2019 2019 1 Jan Capital 2 000 Sales returns 3 600 (1)AO2 Sales 79 200 (1)AO2 Trade payables 40 750 (1)AO3 Rent 6 500 (1)AO2 Postage 8 250 (1)AO2 Office expenses 3 450 Internet costs 5 050 Fixtures 1 300 (1)AO1 Drawings 6 000 (1)AO2 _____ 31 Dec Balance c/d 6 300 81 200 81 200 1 Jan Balance b/d 6 300 (1of)AO1 Calculation of payment to trade payables (7 500 - 200) x £7 = £51 100 – £10 350 = £40 750 (8) (ii) AO1:(3) AO2(3) :AO3(2) AO1: Three marks for transferring balances to statement AO2: Three marks for calculating and recording sales and expenses AO3: Two marks for calculating and recording purchases and closing inventory Natalie Statement of profit or loss and other comprehensive income for the year ended 31 December 2019 £ £ Revenue 79 200 Less Returns (3 600) 75 600 (1)AO2 Opening inventory - Purchases 52 500 Purchase returns (1 400) 51 100 (1)AO3 Closing inventory (7 000) (1)AO3 Cost of sales 44 100 Gross profit 31 500 Less Rent 6 000 (1)AO1 Postage on sales 8 250 (1)AO2 Office expenses 3 450 (1)AO1 Internet costs 5 050 (1)AO1 Depreciation 1 100 (1)AO2 23 850 Profit for the year 7 650 Closing inventory (7 500 – 200) = 7 300 – (6 600 – 300) = 1 000 x £7 = £7 000 (8) (iii) AO1:(2) AO2(4) AO1: Two marks for recording capital and trade payables correctly A02: Four marks for other receivable and totals of sections Statement of financial pos",
          "image": "/papers/wac11-jan-2020/q3-3a.png"
        }
      ],
      "image": "/papers/wac11-jan-2020/page-18.png"
    },
    {
      "id": "q5",
      "number": 5,
      "type": "structured",
      "totalMarks": 1,
      "marks": 1,
      "question": "5 (a) Prepare the Manufacturing Account, in columnar format, for the year ended 31 December 2019, showing the cost of producing desks, tables and a total cost. (20) .........................................................................................................................................................................................................................................",
      "text": "5 (a) Prepare the Manufacturing Account, in columnar format, for the year ended 31 December 2019, showing the cost of producing desks, tables and a total cost. (20) .........................................................................................................................................................................................................................................",
      "parts": [
        {
          "id": "5a",
          "text": "5 (a) Prepare the Manufacturing Account, in columnar format, for the year ended 31 December 2019, showing the cost of producing desks, tables and a total cost. (20) .........................................................................................................................................................................................................................................",
          "marks": 1,
          "type": "structured",
          "answer": "AO1:(5) AO2(12) :AO3(3) AO1: Five marks for transferring balances to statement or totalling sub sections AO2: Twelve marks for calculating expenses, profit or transfer value of each product AO3: Three marks for sub dividing expense and then apportioning Manufacturing Account For the year ended 31 December 2019 Desk Table Total £ £ £ Opening inventory of raw materials 54 000 Purchases of raw materials 193 000 247 000 Closing inventory of raw materials (61 000) Cost of raw materials 112 000 74 000 (1)AO3 186 000 (1)AO1 Production wages 128 000 (1)AO2 80 000 (1)AO2 208 000 Sundry materials 12 000 (1)AO3 6 000 (1)AO3 18 000 Royalties 20 000 (1)AO1 - 20 000 Prime cost (1)AO1 272 000 (1of)AO1 160 000 (1of)AO1 432 000 Production overheads: Sundry materials 8 000 (1)AO2 4 000 12 000 Rent and rates 24 000 (1)AO2 16 000 40 000 Management salaries 40 000 (1)AO2 25 000 65 000 Insurance of machinery 6 000 (1)AO2 9 000 15 000 Electricity 9 600 (1)AO2 7 200 16 800 Depreciation of machinery 12 000 (1)AO2 18 000 30 000 99 600 79 200 178 800 371 600 (1of)AO2 239 200 610 800 Work in progress: 1 January 37 000 24 000 61 000 31 December (38 600) (23 200) (61 800) (1 600) (1)AO2 800 (800) Cost of production 370 000 240 000 610 000 Manufacturing profit 10% 37 000 (1of)AO2 24 000 61 000 Transfer value 407 000 (1of)AO2 264 000 671 000 (20) (b) AO1:(4) AO1: Four marks for explaining the entries The closing inventory of finished goods at 31 December 2019 contains £60 000 (1)AO1 of unrealised profit. The existing balance of the provision for unrealised profit is £70 000, (1)AO1 therefore the difference of £10 000 (1of)AO1 must be DEBITED (1)AO1 to the provision for unrealised profit account using the narrative income statement, which will be balanced and brought down. (4) (c) AO2 (1), AO3 (2), AO4 (3) Positive points for group bonus Workers may work harder and output may increase. The scheme will reward extra effort. Unit costs may decrease. The bonus will be paid only when production figures ",
          "image": "/papers/wac11-jan-2020/q5-5a.png"
        }
      ],
      "image": "/papers/wac11-jan-2020/page-25.png"
    },
    {
      "id": "q6",
      "number": 6,
      "type": "structured",
      "totalMarks": 1,
      "marks": 1,
      "question": "6 (a) Explain the meaning of the following terms as they relate to inventory: (4) • historic cost c oncept .................................................................................................................................................................................................................................................................................... ...............",
      "text": "6 (a) Explain the meaning of the following terms as they relate to inventory: (4) • historic cost c oncept .................................................................................................................................................................................................................................................................................... ...............",
      "parts": [
        {
          "id": "6a",
          "text": "6 (a) Explain the meaning of the following terms as they relate to inventory: (4) • historic cost c oncept .................................................................................................................................................................................................................................................................................... ...............",
          "marks": 1,
          "type": "structured",
          "answer": "AO1:(4) AO1: Four marks for explaining concepts Historic cost concept Inventory should be recorded at cost (1)AO1 at time of purchase / not at its market value (1)AO1 Net realizable value Where realizable value is less than cost, the estimated selling price (1)AO1 less any further costs before the goods are suitable for sale. (1)AO1 (4) (b) AO1:(2) AO2(4) AO1: Two marks for closing inventory AO2: Four marks for sub totals Printers Ink cartridges Number Number Inventory – 1 September 2019 16 120 Purchases 48 290 Sales returns 1 - 65(1)AO2 410 (1)AO1 Less Sales (50) (300) Purchase returns - (16) (50) (1)AO2 (316) (1)AO2 Inventory – 31 December 2019 15 (1)AO1 94 (1)AO1 (6) (c) AO2(4) AO2: Four marks for calculating the percentages Printers 5(1)AO2 x 100 = 6.25% (1)AO2 Ink cartridges 15(1)AO2 x 100 = 60% (1)AO2 (4) (d) A01(3): AO2(4) :AO3(3) AO1: Three marks for correct returns and calculation of total gross profit AO2: Four marks for calculating correct entries AO3: Three marks for calculating correct sales, purchases and closing inventory Statement of Profit or Loss and Other Comprehensive Income for the three months ended 31 December 2019 £ £ Revenue 11 500 (1)AO3 Less returns (80) (1)AO1 11 420 Inventory 2 400 (1)AO2 Purchases 6 500 (1)AO3 Purchases returns (160) (1)AO1 8 740 Inventory (2 065) (1of)AO3 Cost of sales: (6 675)(1of)AO2+W Gross profit 4 745 Expenses 2 135 (1)AO2 Depreciation 600 (1)AO2 2 735 Profit for the three months 2 010 (1of)AO1 (10) Workings Printers Ink cartridges Total £ £ Sales 50@80 300@25 11 500 Sales returns 1@80 - 80 Opening inventory 16@75 120@10 2 400 Purchases 48@75 290@10 6 500 Purchase returns - 16@10 160 Closing inventory 15@75 94@10 2 065 (e) AO2 (1), AO3 (2), AO4 (3) Own figure applies Positive points for strategy Printers offered at competitive prices to customers. Customers buy printer cheaply and then are ‘tied into’ buying ink cartridges. Generates repeat business. A very good gross profit margin achieved on ink cartridges. Nega",
          "image": "/papers/wac11-jan-2020/q6-6a.png"
        }
      ],
      "image": "/papers/wac11-jan-2020/page-30.png"
    }
  ],
  "_meta": {
    "parser": "structured",
    "partCount": 4,
    "questionCount": 4
  },
  "assets": {
    "basePath": "/papers/wac11-jan-2020",
    "qpPdf": "/pdf-pastpaer-q&a/A-Level/Accounting-WAC11/Accounting-WAC11-2020-unit1-2020-01-qp.pdf",
    "pageImages": [
      "/papers/wac11-jan-2020/page-01.png",
      "/papers/wac11-jan-2020/page-02.png",
      "/papers/wac11-jan-2020/page-03.png",
      "/papers/wac11-jan-2020/page-04.png",
      "/papers/wac11-jan-2020/page-05.png",
      "/papers/wac11-jan-2020/page-06.png",
      "/papers/wac11-jan-2020/page-07.png",
      "/papers/wac11-jan-2020/page-08.png",
      "/papers/wac11-jan-2020/page-09.png",
      "/papers/wac11-jan-2020/page-10.png",
      "/papers/wac11-jan-2020/page-11.png",
      "/papers/wac11-jan-2020/page-12.png",
      "/papers/wac11-jan-2020/page-13.png",
      "/papers/wac11-jan-2020/page-14.png",
      "/papers/wac11-jan-2020/page-15.png",
      "/papers/wac11-jan-2020/page-16.png",
      "/papers/wac11-jan-2020/page-17.png",
      "/papers/wac11-jan-2020/page-18.png",
      "/papers/wac11-jan-2020/page-19.png",
      "/papers/wac11-jan-2020/page-20.png",
      "/papers/wac11-jan-2020/page-21.png",
      "/papers/wac11-jan-2020/page-22.png",
      "/papers/wac11-jan-2020/page-23.png",
      "/papers/wac11-jan-2020/page-24.png",
      "/papers/wac11-jan-2020/page-25.png",
      "/papers/wac11-jan-2020/page-26.png",
      "/papers/wac11-jan-2020/page-27.png",
      "/papers/wac11-jan-2020/page-28.png",
      "/papers/wac11-jan-2020/page-29.png",
      "/papers/wac11-jan-2020/page-30.png",
      "/papers/wac11-jan-2020/page-31.png",
      "/papers/wac11-jan-2020/page-32.png",
      "/papers/wac11-jan-2020/page-33.png",
      "/papers/wac11-jan-2020/page-34.png",
      "/papers/wac11-jan-2020/page-35.png",
      "/papers/wac11-jan-2020/page-36.png",
      "/papers/wac11-jan-2020/page-37.png",
      "/papers/wac11-jan-2020/page-38.png",
      "/papers/wac11-jan-2020/page-39.png",
      "/papers/wac11-jan-2020/page-40.png",
      "/papers/wac11-jan-2020/page-41.png",
      "/papers/wac11-jan-2020/page-42.png",
      "/papers/wac11-jan-2020/page-43.png",
      "/papers/wac11-jan-2020/page-44.png",
      "/papers/wac11-jan-2020/page-45.png",
      "/papers/wac11-jan-2020/page-46.png",
      "/papers/wac11-jan-2020/page-47.png",
      "/papers/wac11-jan-2020/page-48.png",
      "/papers/wac11-jan-2020/page-49.png",
      "/papers/wac11-jan-2020/page-50.png",
      "/papers/wac11-jan-2020/page-51.png",
      "/papers/wac11-jan-2020/page-52.png"
    ]
  },
  "unit": "Unit 1"
}